adafruit_spd1656.py
adafruit_circuitpython_spd1656-0.9.6.dist-info/licenses/LICENSE
adafruit_circuitpython_spd1656-0.9.6.dist-info/METADATA
adafruit_circuitpython_spd1656-0.9.6.dist-info/WHEEL
adafruit_circuitpython_spd1656-0.9.6.dist-info/top_level.txt
adafruit_circuitpython_spd1656-0.9.6.dist-info/RECORD
