Metadata-Version: 2.4
Name: adafruit-circuitpython-spd1656
Version: 0.9.6
Summary: Driver for SPD1656 driven ACeP (7-color) e-paper displays
Author-email: Adafruit Industries <circuitpython@adafruit.com>
License: MIT
Project-URL: Homepage, https://github.com/adafruit/Adafruit_CircuitPython_SPD1656
Keywords: adafruit,blinka,circuitpython,micropython,spd1656
Classifier: Intended Audience :: Developers
Classifier: Topic :: Software Development :: Libraries
Classifier: Topic :: Software Development :: Embedded Systems
Classifier: Topic :: System :: Hardware
Classifier: License :: OSI Approved :: MIT License
Classifier: Programming Language :: Python :: 3
License-File: LICENSE
Requires-Dist: Adafruit-Blinka
Requires-Dist: adafruit-blinka-displayio
Provides-Extra: optional
Dynamic: license-file
